aspose/gis/py.typed
aspose/pycore/py.typed
aspose/pycore/__init__.pyi
aspose/pyreflection/py.typed
aspose/pyreflection/__init__.pyi
aspose/pydrawing/py.typed
aspose/pydrawing/__init__.pyi
aspose/pydrawing/design.pyi
aspose/pydrawing/drawing2d.pyi
aspose/pydrawing/imaging.pyi
aspose/pydrawing/printing.pyi
aspose/pydrawing/text.pyi
aspose/gis/__init__.pyi
aspose/gis/common/__init__.pyi
aspose/gis/common/formats/__init__.pyi
aspose/gis/common/formats/dbase/__init__.pyi
aspose/gis/common/formats/gdbtable/__init__.pyi
aspose/gis/common/formats/mapinfo/__init__.pyi
aspose/gis/common/formats/mapinfo/graphicalobjects/__init__.pyi
aspose/gis/common/formats/mapinfo/interchangeformat/__init__.pyi
aspose/gis/common/formats/mapinfo/styling/__init__.pyi
aspose/gis/common/formats/mapinfo/tabformat/__init__.pyi
aspose/gis/common/formats/mapinfo/tabformat/map/__init__.pyi
aspose/gis/common/formats/wkb/__init__.pyi
aspose/gis/common/formats/wkt/__init__.pyi
aspose/gis/common/formats/xml/__init__.pyi
aspose/gis/common/io/__init__.pyi
aspose/gis/epsg/__init__.pyi
aspose/gis/formats/__init__.pyi
aspose/gis/formats/bmpw/__init__.pyi
aspose/gis/formats/csv/__init__.pyi
aspose/gis/formats/database/__init__.pyi
aspose/gis/formats/database/dataediting/__init__.pyi
aspose/gis/formats/database/fromdefinition/__init__.pyi
aspose/gis/formats/esriascii/__init__.pyi
aspose/gis/formats/esrijson/__init__.pyi
aspose/gis/formats/filegdb/__init__.pyi
aspose/gis/formats/gdal/__init__.pyi
aspose/gis/formats/geojson/__init__.pyi
aspose/gis/formats/geojsonseq/__init__.pyi
aspose/gis/formats/geopackage/__init__.pyi
aspose/gis/formats/geotiff/__init__.pyi
aspose/gis/formats/gml/__init__.pyi
aspose/gis/formats/gpx/__init__.pyi
aspose/gis/formats/infile/__init__.pyi
aspose/gis/formats/inmemory/__init__.pyi
aspose/gis/formats/jpegw/__init__.pyi
aspose/gis/formats/kml/__init__.pyi
aspose/gis/formats/kml/specificfields/__init__.pyi
aspose/gis/formats/kml/styles/__init__.pyi
aspose_gis_net-26.1.0.dist-info/METADATA
aspose_gis_net-26.1.0.dist-info/WHEEL
aspose_gis_net-26.1.0.dist-info/entry_points.txt
aspose_gis_net-26.1.0.dist-info/top_level.txt
aspose_gis_net-26.1.0.dist-info/RECORD