Metadata-Version: 2.1
Name: aspose-gis-net
Version: 26.1.0
Summary: Aspose.GIS for Python via .NET is a standalone API to read, write, process, convert GDB, GPX, Shapefile, GML, FileGDB, KML and other popular gis formats. Integration with DataBases and Rendering capabilities of GIS data out from the box.
Home-page: https://products.aspose.com/gis/python-net
Author: Aspose
License: Free To Use But Restricted,Other/Proprietary License
Project-URL: API Reference, https://reference.aspose.com/gis/python-net/
Project-URL: Blog, https://blog.aspose.com/categories/aspose.gis-product-family/
Project-URL: Demos, https://products.aspose.app/gis/family
Project-URL: Docs, https://docs.aspose.com/gis/python-net/
Project-URL: Examples, https://github.com/aspose-gis/Aspose.GIS-for-Python-NET
Project-URL: Free Support, https://forum.aspose.com/c/gis
Project-URL: Release Notes, https://docs.aspose.com/gis/python-net/release-notes/
Project-URL: Temporary License, https://purchase.aspose.com/temporary-license
Keywords: Cartography,map,Geo,Geographic,Geography,Geolocation,Geospatial,GIS,Latitude,Location,Longitude,Map,Mapping,Maps,.net,ascii,aspose,gis,geo,bmp,convert,converter,python,py,wheel,format,geometries,geometry,geoprocessing,generator,geotools,jpg,library,mapinfo,png,raster,render,rendering,srid,svg,tiff,GDB,KML,EPSG,GEOTIFF,GML,GPX,GDB,SHP,WKT,POSTGIS,ARCGIS,FILEGDB,GDBTABLE,SHAPEFILE,GEOJSON,TOPOJSON,MIF,OSM
Platform: win_amd64
Classifier: Development Status :: 5 - Production/Stable
Classifier: Intended Audience :: Developers
Classifier: Intended Audience :: Education
Classifier: Intended Audience :: Other Audience
Classifier: Operating System :: Microsoft :: Windows
Classifier: Operating System :: POSIX :: Linux
Classifier: Operating System :: Unix
Classifier: Operating System :: MacOS :: MacOS X
Classifier: Environment :: MacOS X
Classifier: Topic :: Office/Business
Classifier: Topic :: Software Development
Classifier: Topic :: Software Development :: Libraries
Classifier: Topic :: Multimedia :: Graphics
Classifier: Topic :: Multimedia :: Graphics :: Graphics Conversion
Classifier: Topic :: Scientific/Engineering :: Image Processing
Classifier: Programming Language :: Python :: 3
Classifier: Programming Language :: Python :: 3 :: Only
Classifier: Programming Language :: Python :: 3.5
Classifier: Programming Language :: Python :: 3.6
Classifier: Programming Language :: Python :: 3.7
Classifier: Programming Language :: Python :: 3.8
Classifier: Programming Language :: Python :: 3.9
Classifier: Programming Language :: Python :: 3.10
Classifier: Programming Language :: Python :: 3.11
Classifier: Programming Language :: Python :: 3.12
Classifier: Programming Language :: Python :: 3.13
Requires-Python: >=3.5,<3.14
